magic_dash/__init__.py
magic_dash/templates/magic-dash/app.py
magic_dash/templates/magic-dash/requirements.txt
magic_dash/templates/magic-dash/server.py
magic_dash/templates/magic-dash/assets/favicon.ico
magic_dash/templates/magic-dash/assets/css/base.css
magic_dash/templates/magic-dash/assets/css/core.css
magic_dash/templates/magic-dash/assets/imgs/init_loading.gif
magic_dash/templates/magic-dash/assets/imgs/logo.svg
magic_dash/templates/magic-dash/assets/imgs/status/404.svg
magic_dash/templates/magic-dash/assets/imgs/status/500.svg
magic_dash/templates/magic-dash/assets/js/basic_callbacks.js
magic_dash/templates/magic-dash/callbacks/__init__.py
magic_dash/templates/magic-dash/callbacks/core_pages_c/__init__.py
magic_dash/templates/magic-dash/callbacks/core_pages_c/page1_c.py
magic_dash/templates/magic-dash/components/__init__.py
magic_dash/templates/magic-dash/components/core_side_menu.py
magic_dash/templates/magic-dash/configs/__init__.py
magic_dash/templates/magic-dash/configs/base_config.py
magic_dash/templates/magic-dash/configs/layout_config.py
magic_dash/templates/magic-dash/configs/router_config.py
magic_dash/templates/magic-dash/utils/clear_pycache.py
magic_dash/templates/magic-dash/views/__init__.py
magic_dash/templates/magic-dash/views/core_pages/__init__.py
magic_dash/templates/magic-dash/views/core_pages/independent_page.py
magic_dash/templates/magic-dash/views/core_pages/independent_page_demo.py
magic_dash/templates/magic-dash/views/core_pages/independent_wildcard_page.py
magic_dash/templates/magic-dash/views/core_pages/independent_wildcard_page_demo.py
magic_dash/templates/magic-dash/views/core_pages/index.py
magic_dash/templates/magic-dash/views/core_pages/page1.py
magic_dash/templates/magic-dash/views/core_pages/sub_menu_page1.py
magic_dash/templates/magic-dash/views/core_pages/sub_menu_page2.py
magic_dash/templates/magic-dash/views/core_pages/sub_menu_page3.py
magic_dash/templates/magic-dash/views/core_pages/url_params_page.py
magic_dash-0.4.1.dist-info/licenses/LICENSE
magic_dash-0.4.1.dist-info/METADATA
magic_dash-0.4.1.dist-info/WHEEL
magic_dash-0.4.1.dist-info/entry_points.txt
magic_dash-0.4.1.dist-info/top_level.txt
magic_dash-0.4.1.dist-info/RECORD
