Metadata-Version: 2.4
Name: magic_dash
Version: 0.4.1
Summary: A command-line tool for quickly generating standard Dash application projects.
Home-page: https://github.com/CNFeffery/magic-dash
Author: CNFeffery <fefferypzy@gmail.com>
Author-email: fefferypzy@gmail.com
License: MIT
Classifier: Framework :: Dash
Requires-Python: >=3.8, <3.14
License-File: LICENSE
Requires-Dist: click
Dynamic: author
Dynamic: author-email
Dynamic: classifier
Dynamic: description
Dynamic: description-content-type
Dynamic: home-page
Dynamic: license
Dynamic: license-file
Dynamic: requires-dist
Dynamic: requires-python
Dynamic: summary
